{
  "_comment": "Action space used by pipeline/dual_vlm_gate VLM prompts.",
  "groups": {
    "dual_scene": {
      "actions": {
        "A_SCALE_UP_10": {},
        "A_SCALE_DOWN_10": {},
        "B_SCALE_UP_10": {},
        "B_SCALE_DOWN_10": {},
        "A_LIFT_SMALL": {},
        "A_LOWER_SMALL": {},
        "B_LIFT_SMALL": {},
        "B_LOWER_SMALL": {},
        "A_LIFT_TINY": {},
        "A_LOWER_TINY": {},
        "B_LIFT_TINY": {},
        "B_LOWER_TINY": {},
        "A_GROUND_SNAP": {},
        "B_GROUND_SNAP": {},
        "BOTH_GROUND_SNAP": {},
        "A_ROTATE_Z_POS_15": {},
        "A_ROTATE_Z_NEG_15": {},
        "B_ROTATE_Z_POS_15": {},
        "B_ROTATE_Z_NEG_15": {},
        "PAIR_INCREASE_DISTANCE": {},
        "PAIR_DECREASE_DISTANCE": {},
        "PAIR_B_HIGHER": {},
        "PAIR_B_LOWER": {},
        "CAMERA_WIDER": {},
        "CAMERA_CLOSER": {},
        "CAMERA_AZ_POS_15": {},
        "CAMERA_AZ_NEG_15": {},
        "CAMERA_ELEVATION_UP": {},
        "CAMERA_ELEVATION_DOWN": {},
        "CAMERA_FOCAL_WIDER": {},
        "CAMERA_FOCAL_TIGHTER": {},
        "FRAMING_MARGIN_DOWN": {},
        "FRAMING_MARGIN_UP": {},
        "L_SPOT_UP": {},
        "L_SPOT_DOWN": {},
        "L_FILL_UP": {},
        "L_FILL_DOWN": {},
        "L_SPOT_HIGHER": {},
        "L_SPOT_LOWER": {},
        "L_SPOT_WIDER": {},
        "L_SPOT_NARROWER": {},
        "ENV_STRENGTH_UP": {},
        "ENV_STRENGTH_DOWN": {},
        "SCENE_LIGHTS_DOWN": {},
        "SCENE_LIGHTS_UP": {},
        "SCENE_AREA_LIGHTS_DOWN": {},
        "SCENE_POINT_LIGHTS_DOWN": {},
        "SCENE_SPOT_LIGHTS_DOWN": {},
        "SCENE_SUN_LIGHTS_DOWN": {},
        "SCENE_LIGHTS_CLAMP_STRONG": {},
        "CONTACT_SHADOW_UP": {},
        "AO_UP": {},
        "AO_DOWN": {},
        "A_SATURATION_UP": {},
        "B_SATURATION_UP": {},
        "A_SATURATION_DOWN": {},
        "B_SATURATION_DOWN": {},
        "A_VALUE_DOWN": {},
        "B_VALUE_DOWN": {},
        "A_VALUE_UP": {},
        "B_VALUE_UP": {},
        "A_CONTRAST_UP": {},
        "B_CONTRAST_UP": {}
      }
    }
  },
  "compound_actions": {}
}
